<?xml version='1.0' encoding='utf-8'?>
<root version="20190819">
    <world>
        <walls>
            <wall stroke-width="0" begin="12.0263:244.251" stroke="#ff000000" stroke-style="none" id="wall1" end="253.574:242.949" fill="#ff000000"/>
            <wall stroke-width="0" begin="253.983:244.134" stroke="#ff000000" stroke-style="none" id="wall2" end="255.417:423.466" fill="#ff000000"/>
        </walls>
        <skittles>
            <skittle x="-206.6" rotation="0" y="-75.03" markerX="-206.6" startRotation="0" id="skittle1" markerY="-75.03"/>
        </skittles>
        <balls>
            <ball x="564.143" rotation="0" y="-4.21967" markerX="96.8" startRotation="0" id="ball1" markerY="167.8"/>
            <ball x="539.206" rotation="0" y="193.574" markerX="156.4" startRotation="0" id="ball2" markerY="187.8"/>
            <ball x="654.092" rotation="0" y="259.104" markerX="238.9" startRotation="0" id="ball3" markerY="168.7"/>
        </balls>
        <colorFields/>
        <images/>
        <regions/>
    </world>
    <robots>
        <robot id="trikKitRobot" direction="-101.328" position="268.885:-85.9374">
            <sensors>
                <sensor port="M3###output###М3###" direction="0" position="25:25" type="kitBase::robotModel::robotParts::Motor"/>
                <sensor port="M4###output###М4###" direction="0" position="25:25" type="kitBase::robotModel::robotParts::Motor"/>
                <sensor port="M1###output###М1###" direction="0" position="25:25" type="kitBase::robotModel::robotParts::Motor"/>
                <sensor port="M2###output###М2###" direction="0" position="25:25" type="kitBase::robotModel::robotParts::Motor"/>
            </sensors>
            <startPosition x="13.7" y="152.55" id="{4254c5bc-e090-4c9e-8df6-cd29f7978408}" direction="0"/>
            <wheels right="M3###output###М3###" left="M4###output###М4###"/>
        </robot>
    </robots>
    <settings realisticPhysics="true" realisticMotors="false" realisticSensors="false"/>
</root>
